kakaowork_alarm/__init__.py
kakaowork_alarm/api.py
kakaowork_api/__init__.py
kakaowork_api/api.py
kakaowork_alarm-0.0.1.dist-info/METADATA
kakaowork_alarm-0.0.1.dist-info/WHEEL
kakaowork_alarm-0.0.1.dist-info/top_level.txt
kakaowork_alarm-0.0.1.dist-info/RECORD
