Metadata-Version: 2.1
Name: kakaowork-alarm
Version: 0.0.1
Home-page: 
Author: archon.oh
Author-email: archon.oh@knworks.co.kr
Keywords: knw,kakaowork,kakaoworkapi,work
Requires-Python: >=3.6
Requires-Dist: requests
